brainview/__init__.py
brainview/atlasviewer.py
brainview/brainviewer.py
brainview/dev_tools.py
brainview/export.py
brainview/multiview.py
brainview/singleview.py
brainview/util.py
brainview-0.0.1.dist-info/LICENSE
brainview-0.0.1.dist-info/METADATA
brainview-0.0.1.dist-info/WHEEL
brainview-0.0.1.dist-info/entry_points.txt
brainview-0.0.1.dist-info/top_level.txt
brainview-0.0.1.dist-info/RECORD
