Metadata-Version: 2.1
Name: brainview
Version: 0.0.1
Summary: Visualize morphometry neuroimaging data on 3D brain meshes.
Home-page: https://github.com/dfsp-spirit/brainview
Author: Tim Schäfer
Author-email: UNKNOWN
License: MIT
Keywords: neuroimaging freesurfer visualize plot 3D brain morphometry MRI
Platform: UNKNOWN
Classifier: Development Status :: 2 - Pre-Alpha
Classifier: Intended Audience :: Developers
Classifier: Intended Audience :: Science/Research
Classifier: License :: OSI Approved :: MIT License
Classifier: Programming Language :: Python :: 2
Classifier: Programming Language :: Python :: 2.7
Classifier: Programming Language :: Python :: 3
Classifier: Programming Language :: Python :: 3.4
Classifier: Programming Language :: Python :: 3.5
Classifier: Programming Language :: Python :: 3.6
Requires-Dist: numpy
Requires-Dist: nibabel
Requires-Dist: matplotlib
Requires-Dist: mayavi
Requires-Dist: vtk
Requires-Dist: brainload (>=0.3.2)
